prefix_grouper/__init__.py
prefix_grouper/__version__.py
prefix_grouper/forward.py
prefix_grouper/function.py
prefix_grouper/info.py
prefix_grouper/utils/__init__.py
prefix_grouper/utils/mask.py
prefix_grouper/utils/register_transformers.py
prefix_grouper/utils/typing.py
prefix_grouper-0.0.1.post1.dist-info/licenses/LICENSE
prefix_grouper-0.0.1.post1.dist-info/METADATA
prefix_grouper-0.0.1.post1.dist-info/WHEEL
prefix_grouper-0.0.1.post1.dist-info/top_level.txt
prefix_grouper-0.0.1.post1.dist-info/RECORD
