Metadata-Version: 2.4
Name: prefix_grouper
Version: 0.0.1.post1
Summary: An efficient GRPO training util.
Author-email: Zikang Liu <liuzikang0625@gmail.com>
License: MIT
Project-URL: Homepage, https://github.com/johncaged/PrefixGrouper
Classifier: Programming Language :: Python :: 3
Classifier: License :: OSI Approved :: MIT License
Classifier: Operating System :: OS Independent
Requires-Python: >=3.8
License-File: LICENSE
Dynamic: license-file
